terpy/__init__.py
terpy/__version__.py
terpy/structures.py
terpy/plot/__init__.py
terpy/plot/energy_diagram.py
TerPy-0.0.1.dist-info/LICENSE
TerPy-0.0.1.dist-info/METADATA
TerPy-0.0.1.dist-info/WHEEL
TerPy-0.0.1.dist-info/top_level.txt
TerPy-0.0.1.dist-info/RECORD
