Metadata-Version: 2.1
Name: TerPy
Version: 0.0.1
Summary: Computational chemistry utilities.
Home-page: 
Author: Sebastian Wellig
Author-email: sebastian.wellig@gmail.com
License: MIT license
Platform: UNKNOWN
Requires-Python: >=3.6.*
License-File: LICENSE
Requires-Dist: numpy
Requires-Dist: scipy
Requires-Dist: matplotlib
